{
  "format-version" : 2,
  "table-uuid" : "67f7ebbb-8105-4ba5-b1a2-dc37545ae269",
  "location" : "/Users/vishnuch/work/gitcode/bytespireio/streamlana/data/iceberg_crashes/db/crashes_cube",
  "last-sequence-number" : 6,
  "last-updated-ms" : 1750651650037,
  "last-column-id" : 35,
  "current-schema-id" : 0,
  "schemas" : [ {
    "type" : "struct",
    "schema-id" : 0,
    "fields" : [ {
      "id" : 1,
      "name" : "crash_day",
      "required" : false,
      "type" : "date"
    }, {
      "id" : 2,
      "name" : "is_am",
      "required" : false,
      "type" : "boolean"
    }, {
      "id" : 3,
      "name" : "total_damage",
      "required" : false,
      "type" : "int"
    }, {
      "id" : 4,
      "name" : "total_injured",
      "required" : false,
      "type" : "int"
    }, {
      "id" : 5,
      "name" : "total_fatal",
      "required" : false,
      "type" : "int"
    }, {
      "id" : 6,
      "name" : "weather_condition",
      "required" : false,
      "type" : "string"
    }, {
      "id" : 7,
      "name" : "lighting_condition",
      "required" : false,
      "type" : "string"
    }, {
      "id" : 8,
      "name" : "is_hit_run",
      "required" : false,
      "type" : "boolean"
    }, {
      "id" : 9,
      "name" : "street_name",
      "required" : false,
      "type" : "string"
    }, {
      "id" : 10,
      "name" : "lat",
      "required" : false,
      "type" : "double"
    }, {
      "id" : 11,
      "name" : "lon",
      "required" : false,
      "type" : "double"
    }, {
      "id" : 12,
      "name" : "road_defect",
      "required" : false,
      "type" : "string"
    }, {
      "id" : 13,
      "name" : "is_cell_phone_use",
      "required" : false,
      "type" : "boolean"
    }, {
      "id" : 14,
      "name" : "is_drunk",
      "required" : false,
      "type" : "boolean"
    }, {
      "id" : 15,
      "name" : "list_of_hospital",
      "required" : false,
      "type" : {
        "type" : "list",
        "element-id" : 31,
        "element" : "string",
        "element-required" : false
      }
    }, {
      "id" : 16,
      "name" : "list_of_gender",
      "required" : false,
      "type" : {
        "type" : "list",
        "element-id" : 32,
        "element" : "string",
        "element-required" : false
      }
    }, {
      "id" : 17,
      "name" : "is_age_below_5",
      "required" : false,
      "type" : "boolean"
    }, {
      "id" : 18,
      "name" : "is_age_10s",
      "required" : false,
      "type" : "boolean"
    }, {
      "id" : 19,
      "name" : "is_age_20s",
      "required" : false,
      "type" : "boolean"
    }, {
      "id" : 20,
      "name" : "is_age_30s",
      "required" : false,
      "type" : "boolean"
    }, {
      "id" : 21,
      "name" : "is_age_40s",
      "required" : false,
      "type" : "boolean"
    }, {
      "id" : 22,
      "name" : "is_age_50s",
      "required" : false,
      "type" : "boolean"
    }, {
      "id" : 23,
      "name" : "is_age_senior",
      "required" : false,
      "type" : "boolean"
    }, {
      "id" : 24,
      "name" : "list_of_airbag_deployed",
      "required" : false,
      "type" : {
        "type" : "list",
        "element-id" : 33,
        "element" : "string",
        "element-required" : false
      }
    }, {
      "id" : 25,
      "name" : "vehicle_uses",
      "required" : false,
      "type" : {
        "type" : "list",
        "element-id" : 34,
        "element" : "string",
        "element-required" : false
      }
    }, {
      "id" : 26,
      "name" : "vehicle_makes",
      "required" : false,
      "type" : {
        "type" : "list",
        "element-id" : 35,
        "element" : "string",
        "element-required" : false
      }
    }, {
      "id" : 27,
      "name" : "fire_happened",
      "required" : false,
      "type" : "boolean"
    }, {
      "id" : 28,
      "name" : "hazmat_involved",
      "required" : false,
      "type" : "boolean"
    }, {
      "id" : 29,
      "name" : "total_people_involved",
      "required" : false,
      "type" : "int"
    }, {
      "id" : 30,
      "name" : "crashes_set_sketch",
      "required" : false,
      "type" : "binary"
    } ]
  } ],
  "default-spec-id" : 0,
  "partition-specs" : [ {
    "spec-id" : 0,
    "fields" : [ {
      "name" : "crash_day_day",
      "transform" : "day",
      "source-id" : 1,
      "field-id" : 1000
    } ]
  } ],
  "last-partition-id" : 1000,
  "default-sort-order-id" : 0,
  "sort-orders" : [ {
    "order-id" : 0,
    "fields" : [ ]
  } ],
  "properties" : {
    "owner" : "vishnuch",
    "write.parquet.compression-codec" : "zstd"
  },
  "current-snapshot-id" : 8852866436943920763,
  "refs" : {
    "main" : {
      "snapshot-id" : 8852866436943920763,
      "type" : "branch"
    }
  },
  "snapshots" : [ {
    "sequence-number" : 1,
    "snapshot-id" : 3303943948096215032,
    "timestamp-ms" : 1750651375560,
    "summary" : {
      "operation" : "overwrite",
      "spark.app.id" : "local-1750651365154",
      "replace-partitions" : "true",
      "added-data-files" : "2",
      "added-records" : "249",
      "added-files-size" : "29923",
      "changed-partition-count" : "2",
      "total-records" : "249",
      "total-files-size" : "29923",
      "total-data-files" : "2",
      "total-delete-files" : "0",
      "total-position-deletes" : "0",
      "total-equality-deletes" : "0",
      "engine-version" : "3.5.2",
      "app-id" : "local-1750651365154",
      "engine-name" : "spark",
      "iceberg-version" : "Apache Iceberg 1.8.1 (commit 9ce0fcf0af7becf25ad9fc996c3bad2afdcfd33d)"
    },
    "manifest-list" : "/Users/vishnuch/work/gitcode/bytespireio/streamlana/data/iceberg_crashes/db/crashes_cube/metadata/snap-3303943948096215032-1-eb81802b-fbf5-4c3d-a27b-8efed3507e67.avro",
    "schema-id" : 0
  }, {
    "sequence-number" : 2,
    "snapshot-id" : 3194888749258687614,
    "parent-snapshot-id" : 3303943948096215032,
    "timestamp-ms" : 1750651430147,
    "summary" : {
      "operation" : "overwrite",
      "spark.app.id" : "local-1750651418614",
      "replace-partitions" : "true",
      "added-data-files" : "3",
      "deleted-data-files" : "2",
      "added-records" : "519",
      "deleted-records" : "249",
      "added-files-size" : "48835",
      "removed-files-size" : "29923",
      "changed-partition-count" : "3",
      "total-records" : "519",
      "total-files-size" : "48835",
      "total-data-files" : "3",
      "total-delete-files" : "0",
      "total-position-deletes" : "0",
      "total-equality-deletes" : "0",
      "engine-version" : "3.5.2",
      "app-id" : "local-1750651418614",
      "engine-name" : "spark",
      "iceberg-version" : "Apache Iceberg 1.8.1 (commit 9ce0fcf0af7becf25ad9fc996c3bad2afdcfd33d)"
    },
    "manifest-list" : "/Users/vishnuch/work/gitcode/bytespireio/streamlana/data/iceberg_crashes/db/crashes_cube/metadata/snap-3194888749258687614-1-9f1c9eb4-09a9-4a9d-92be-166b13a34ca5.avro",
    "schema-id" : 0
  }, {
    "sequence-number" : 3,
    "snapshot-id" : 5830881127702410347,
    "parent-snapshot-id" : 3194888749258687614,
    "timestamp-ms" : 1750651481040,
    "summary" : {
      "operation" : "overwrite",
      "spark.app.id" : "local-1750651469068",
      "replace-partitions" : "true",
      "added-data-files" : "4",
      "deleted-data-files" : "3",
      "added-records" : "801",
      "deleted-records" : "519",
      "added-files-size" : "67936",
      "removed-files-size" : "48835",
      "changed-partition-count" : "4",
      "total-records" : "801",
      "total-files-size" : "67936",
      "total-data-files" : "4",
      "total-delete-files" : "0",
      "total-position-deletes" : "0",
      "total-equality-deletes" : "0",
      "engine-version" : "3.5.2",
      "app-id" : "local-1750651469068",
      "engine-name" : "spark",
      "iceberg-version" : "Apache Iceberg 1.8.1 (commit 9ce0fcf0af7becf25ad9fc996c3bad2afdcfd33d)"
    },
    "manifest-list" : "/Users/vishnuch/work/gitcode/bytespireio/streamlana/data/iceberg_crashes/db/crashes_cube/metadata/snap-5830881127702410347-1-bdf36d7d-1377-4024-a659-7fa6f6f699f5.avro",
    "schema-id" : 0
  }, {
    "sequence-number" : 4,
    "snapshot-id" : 5816477885335552570,
    "parent-snapshot-id" : 5830881127702410347,
    "timestamp-ms" : 1750651535182,
    "summary" : {
      "operation" : "overwrite",
      "spark.app.id" : "local-1750651523931",
      "replace-partitions" : "true",
      "added-data-files" : "5",
      "deleted-data-files" : "4",
      "added-records" : "1062",
      "deleted-records" : "801",
      "added-files-size" : "86306",
      "removed-files-size" : "67936",
      "changed-partition-count" : "5",
      "total-records" : "1062",
      "total-files-size" : "86306",
      "total-data-files" : "5",
      "total-delete-files" : "0",
      "total-position-deletes" : "0",
      "total-equality-deletes" : "0",
      "engine-version" : "3.5.2",
      "app-id" : "local-1750651523931",
      "engine-name" : "spark",
      "iceberg-version" : "Apache Iceberg 1.8.1 (commit 9ce0fcf0af7becf25ad9fc996c3bad2afdcfd33d)"
    },
    "manifest-list" : "/Users/vishnuch/work/gitcode/bytespireio/streamlana/data/iceberg_crashes/db/crashes_cube/metadata/snap-5816477885335552570-1-76980732-fc9a-4ea7-988d-ee73b71ece33.avro",
    "schema-id" : 0
  }, {
    "sequence-number" : 5,
    "snapshot-id" : 7209709101558351584,
    "parent-snapshot-id" : 5816477885335552570,
    "timestamp-ms" : 1750651593669,
    "summary" : {
      "operation" : "overwrite",
      "spark.app.id" : "local-1750651582210",
      "replace-partitions" : "true",
      "added-data-files" : "6",
      "deleted-data-files" : "5",
      "added-records" : "1306",
      "deleted-records" : "1062",
      "added-files-size" : "103904",
      "removed-files-size" : "86306",
      "changed-partition-count" : "6",
      "total-records" : "1306",
      "total-files-size" : "103904",
      "total-data-files" : "6",
      "total-delete-files" : "0",
      "total-position-deletes" : "0",
      "total-equality-deletes" : "0",
      "engine-version" : "3.5.2",
      "app-id" : "local-1750651582210",
      "engine-name" : "spark",
      "iceberg-version" : "Apache Iceberg 1.8.1 (commit 9ce0fcf0af7becf25ad9fc996c3bad2afdcfd33d)"
    },
    "manifest-list" : "/Users/vishnuch/work/gitcode/bytespireio/streamlana/data/iceberg_crashes/db/crashes_cube/metadata/snap-7209709101558351584-1-5da18835-1d55-400b-9554-58fb41f18330.avro",
    "schema-id" : 0
  }, {
    "sequence-number" : 6,
    "snapshot-id" : 8852866436943920763,
    "parent-snapshot-id" : 7209709101558351584,
    "timestamp-ms" : 1750651650037,
    "summary" : {
      "operation" : "overwrite",
      "spark.app.id" : "local-1750651637677",
      "replace-partitions" : "true",
      "added-data-files" : "7",
      "deleted-data-files" : "6",
      "added-records" : "1575",
      "deleted-records" : "1306",
      "added-files-size" : "122303",
      "removed-files-size" : "103904",
      "changed-partition-count" : "7",
      "total-records" : "1575",
      "total-files-size" : "122303",
      "total-data-files" : "7",
      "total-delete-files" : "0",
      "total-position-deletes" : "0",
      "total-equality-deletes" : "0",
      "engine-version" : "3.5.2",
      "app-id" : "local-1750651637677",
      "engine-name" : "spark",
      "iceberg-version" : "Apache Iceberg 1.8.1 (commit 9ce0fcf0af7becf25ad9fc996c3bad2afdcfd33d)"
    },
    "manifest-list" : "/Users/vishnuch/work/gitcode/bytespireio/streamlana/data/iceberg_crashes/db/crashes_cube/metadata/snap-8852866436943920763-1-6f3588da-cce7-43d7-b1fd-bace09c0c4b6.avro",
    "schema-id" : 0
  } ],
  "statistics" : [ ],
  "partition-statistics" : [ ],
  "snapshot-log" : [ {
    "timestamp-ms" : 1750651375560,
    "snapshot-id" : 3303943948096215032
  }, {
    "timestamp-ms" : 1750651430147,
    "snapshot-id" : 3194888749258687614
  }, {
    "timestamp-ms" : 1750651481040,
    "snapshot-id" : 5830881127702410347
  }, {
    "timestamp-ms" : 1750651535182,
    "snapshot-id" : 5816477885335552570
  }, {
    "timestamp-ms" : 1750651593669,
    "snapshot-id" : 7209709101558351584
  }, {
    "timestamp-ms" : 1750651650037,
    "snapshot-id" : 8852866436943920763
  } ],
  "metadata-log" : [ {
    "timestamp-ms" : 1750651375187,
    "metadata-file" : "/Users/vishnuch/work/gitcode/bytespireio/streamlana/data/iceberg_crashes/db/crashes_cube/metadata/v1.metadata.json"
  }, {
    "timestamp-ms" : 1750651375560,
    "metadata-file" : "/Users/vishnuch/work/gitcode/bytespireio/streamlana/data/iceberg_crashes/db/crashes_cube/metadata/v2.metadata.json"
  }, {
    "timestamp-ms" : 1750651430147,
    "metadata-file" : "/Users/vishnuch/work/gitcode/bytespireio/streamlana/data/iceberg_crashes/db/crashes_cube/metadata/v3.metadata.json"
  }, {
    "timestamp-ms" : 1750651481040,
    "metadata-file" : "/Users/vishnuch/work/gitcode/bytespireio/streamlana/data/iceberg_crashes/db/crashes_cube/metadata/v4.metadata.json"
  }, {
    "timestamp-ms" : 1750651535182,
    "metadata-file" : "/Users/vishnuch/work/gitcode/bytespireio/streamlana/data/iceberg_crashes/db/crashes_cube/metadata/v5.metadata.json"
  }, {
    "timestamp-ms" : 1750651593669,
    "metadata-file" : "/Users/vishnuch/work/gitcode/bytespireio/streamlana/data/iceberg_crashes/db/crashes_cube/metadata/v6.metadata.json"
  } ]
}